pcs/__init__.py
pcs/__main__.py
pcs/__meta__.py
pcs/_constants.py
pcs/_utils.py
pcs/card_shuffle.py
pcs/command_line.py
pcs/gui.py
pcs/assets/sqwiggle_b_16.png
pcs/assets/sqwiggle_b_32.png
pseudo_card_shuffle-0.0.2.dist-info/licenses/LICENSE.md
pseudo_card_shuffle-0.0.2.dist-info/METADATA
pseudo_card_shuffle-0.0.2.dist-info/WHEEL
pseudo_card_shuffle-0.0.2.dist-info/entry_points.txt
pseudo_card_shuffle-0.0.2.dist-info/top_level.txt
pseudo_card_shuffle-0.0.2.dist-info/RECORD
