Metadata-Version: 2.4
Name: pseudo_card_shuffle
Version: 0.0.2
Summary: For producing a pseudo-randomized list of playing cards (♠️♦️♣️♥️). A (p)seudo (c)ard (s)huffle.
Author-email: Barry Harris <bharrisaplus@gmail.com>
License-Expression: GPL-3.0
Project-URL: Repository, https://github.com/bharrisaplus/pcs_py_pkg
Keywords: cards,shuffle,playing cards
Classifier: Development Status :: 4 - Beta
Classifier: Programming Language :: Python :: 3
Requires-Python: >=3.10
License-File: LICENSE.md
Requires-Dist: pillow
Requires-Dist: supports-color
Dynamic: license-file
